asgi_background/__init__.py
asgi_background/_background_tasks.py
asgi_background/_middleware.py
asgi_background/_types.py
asgi_background/py.typed
asgi_background-0.2.2.dist-info/LICENSE.txt
asgi_background-0.2.2.dist-info/WHEEL
asgi_background-0.2.2.dist-info/METADATA
asgi_background-0.2.2.dist-info/RECORD
