Metadata-Version: 2.1
Name: asgi-background
Version: 0.2.2
Summary: Background tasks for any ASGI web framework
Home-page: https://github.com/adriangb/asgi-background
License: MIT
Keywords: web-framework,http,asgi
Author: Adrian Garcia Badaracco
Author-email: adrian@adriangb.com
Requires-Python: >=3.7,<4
Classifier: Development Status :: 3 - Alpha
Classifier: Environment :: Web Environment
Classifier: Framework :: AsyncIO
Classifier: Intended Audience :: Developers
Classifier: Intended Audience :: Information Technology
Classifier: Intended Audience :: System Administrators
Classifier: License :: OSI Approved :: MIT License
Classifier: Operating System :: OS Independent
Classifier: Programming Language :: Python
Classifier: Programming Language :: Python :: 3
Classifier: Programming Language :: Python :: 3.7
Classifier: Programming Language :: Python :: 3.8
Classifier: Programming Language :: Python :: 3.9
Classifier: Programming Language :: Python :: 3.10
Classifier: Programming Language :: Python :: 3.11
Classifier: Programming Language :: Python :: 3
Classifier: Programming Language :: Python :: 3 :: Only
Classifier: Programming Language :: Python :: 3.10
Classifier: Programming Language :: Python :: 3.7
Classifier: Programming Language :: Python :: 3.8
Classifier: Programming Language :: Python :: 3.9
Classifier: Topic :: Internet
Classifier: Topic :: Internet :: WWW/HTTP
Classifier: Topic :: Internet :: WWW/HTTP :: HTTP Servers
Classifier: Topic :: Software Development
Classifier: Topic :: Software Development :: Libraries
Classifier: Topic :: Software Development :: Libraries :: Application Frameworks
Classifier: Topic :: Software Development :: Libraries :: Python Modules
Classifier: Typing :: Typed
Requires-Dist: anyio (>=3.6.1)
Requires-Dist: asgi-lifespan-middleware (>=0.1.3)
Requires-Dist: typing-extensions (>=4.2.0); python_version < "3.10"
Project-URL: Documentation, https://github.com/adriangb/asgi-background
Project-URL: Repository, https://github.com/adriangb/asgi-background
